MANIFEST.in
README.rst
setup.py
openaero/__init__.py
openaero.egg-info/PKG-INFO
openaero.egg-info/SOURCES.txt
openaero.egg-info/dependency_links.txt
openaero.egg-info/not-zip-safe
openaero.egg-info/requires.txt
openaero.egg-info/top_level.txt