Metadata-Version: 1.0
Name: openaero
Version: 0.1
Summary: Set of tools to project an aircraft
Home-page: https://github.com/CeuAzul/OpenAero
Author: Ceu Azul Aeronaves
Author-email: rafael.lehmkuhl93@gmail.com
License: MIT
Platform: UNKNOWN
